time_tracker/__init__.py
time_tracker/__main__.py
time_tracker/cli.py
time_tracker/db.py
time_tracker/tests/__init__.py
time_tracker/tests/test_time_tracker.py
time_tracker/time_tracker.py
tiempo_tracker-0.1.1.dist-info/entry_points.txt
tiempo_tracker-0.1.1.dist-info/LICENSE
tiempo_tracker-0.1.1.dist-info/WHEEL
tiempo_tracker-0.1.1.dist-info/METADATA
tiempo_tracker-0.1.1.dist-info/RECORD
