Metadata-Version: 2.1
Name: tiempo-tracker
Version: 0.1.1
Summary: Easy to use CLI time tracker written in Python
Home-page: https://github.com/dmikhr/tiempo-tracker
License: MIT
Keywords: time tracker,management,CLI
Author: Dmitrii Khramtsov
Author-email: dmitrypkh@gmail.com
Requires-Python: >=3.9,<4.0
Classifier: License :: OSI Approved :: MIT License
Classifier: Operating System :: OS Independent
Classifier: Programming Language :: Python :: 3
Classifier: Programming Language :: Python :: 3.10
Classifier: Programming Language :: Python :: 3.9
Requires-Dist: SQLAlchemy (>=1.4.41,<2.0.0)
Requires-Dist: appdirs (>=1.4.4,<2.0.0)
Project-URL: Repository, https://github.com/dmikhr/tiempo-tracker
